setup.py
python_pttcrawler/Article.py
python_pttcrawler/Board.py
python_pttcrawler/Global.py
python_pttcrawler/Logger.py
python_pttcrawler/Page.py
python_pttcrawler/WebRetriever.py
python_pttcrawler/__init__.py
python_pttcrawler.egg-info/PKG-INFO
python_pttcrawler.egg-info/SOURCES.txt
python_pttcrawler.egg-info/dependency_links.txt
python_pttcrawler.egg-info/requires.txt
python_pttcrawler.egg-info/top_level.txt